d1y/__init__.py
dyd-0.0.1.dist-info/METADATA
dyd-0.0.1.dist-info/WHEEL
dyd-0.0.1.dist-info/top_level.txt
dyd-0.0.1.dist-info/RECORD
