Metadata-Version: 2.4
Name: dyd
Version: 0.0.1
Summary: Done tools.
Author-email: Ding Yi <donexistence@gmail.com>
License-Expression: MIT
